maison_jung/__init__.py
maison_jung/cli.py
maison_jung/scheduler/__init__.py
maison_jung/scheduler/jobs.py
maison_jung/scheduler/main.py
maison_jung/server/__init__.py
maison_jung/server/actions.py
maison_jung/server/adafruit.py
maison_jung/server/files.py
maison_jung/server/main.py
maison_jung/telegram_bot/__init__.py
maison_jung/telegram_bot/actions.py
maison_jung/telegram_bot/core.py
maison_jung/telegram_bot/database.py
maison_jung/telegram_bot/main.py
maison_jung/telegram_bot/menus.py
maison_jung/utils.py
maison_jung-0.1.9.dist-info/METADATA
maison_jung-0.1.9.dist-info/WHEEL
maison_jung-0.1.9.dist-info/entry_points.txt
maison_jung-0.1.9.dist-info/RECORD
